<?xml version="1.0" encoding="utf-8" ?>

<devices>
	
	<device nameDevice = "PNK-3V">
	
		<initialPositions>
			
			<control name = "c#0#">
					<position>1</position>
			

				<uprav>
					<name>Разъем «Ш1»</name>
					<poloz>подключен</poloz>
				</uprav>

				<luft>
					<left>0</left>
					<right>0</right>
				</luft>

				<UpravWork>
					<proverkaNU>true</proverkaNU>
					<proverkaPZI>true</proverkaPZI>
				</UpravWork>

				<LinkUprav>
					<LinkToIMG>KPAengine\Pic KPA\Спеки.docx</LinkToIMG>
					<vinoska>с0</vinoska>
				</LinkUprav>
</control>
			
			<control name = "c#1#">
					<position>0</position>
			

				<uprav>
					<name>Разъем «Ш2»</name>
					<poloz>не подключен</poloz>
				</uprav>

				<luft>
					<left>0</left>
					<right>0</right>
				</luft>

				<UpravWork>
					<proverkaNU>true</proverkaNU>
					<proverkaPZI>true</proverkaPZI>
				</UpravWork>

				<LinkUprav>
					<LinkToIMG>KPAengine\Pic KPA\Спеки.docx</LinkToIMG>
					<vinoska>с1</vinoska>
				</LinkUprav>
</control>
			
			<control name = "c#2#">
					<position>0</position>
			

				<uprav>
					<name>Разъем «Ш4»</name>
					<poloz>не подключен</poloz>
				</uprav>

				<luft>
					<left>0</left>
					<right>0</right>
				</luft>

				<UpravWork>
					<proverkaNU>true</proverkaNU>
					<proverkaPZI>true</proverkaPZI>
				</UpravWork>

				<LinkUprav>
					<LinkToIMG>KPAengine\Pic KPA\Спеки.docx</LinkToIMG>
					<vinoska>с2</vinoska>
				</LinkUprav>
</control>
			
			<control name = "c#3#">
					<position>0</position>
			

				<uprav>
					<name>Разъем «Ш5»</name>
					<poloz>не подключен</poloz>
				</uprav>

				<luft>
					<left>0</left>
					<right>0</right>
				</luft>

				<UpravWork>
					<proverkaNU>true</proverkaNU>
					<proverkaPZI>true</proverkaPZI>
				</UpravWork>

				<LinkUprav>
					<LinkToIMG>KPAengine\Pic KPA\Спеки.docx</LinkToIMG>
					<vinoska>с3</vinoska>
				</LinkUprav>
</control>
			
			<control name = "c#4#">
					<position>0</position>
			

				<uprav>
					<name>Разъем «Ш3»</name>
					<poloz>не подключен</poloz>
				</uprav>

				<luft>
					<left>0</left>
					<right>0</right>
				</luft>

				<UpravWork>
					<proverkaNU>true</proverkaNU>
					<proverkaPZI>true</proverkaPZI>
				</UpravWork>

				<LinkUprav>
					<LinkToIMG>KPAengine\Pic KPA\Спеки.docx</LinkToIMG>
					<vinoska>с4</vinoska>
				</LinkUprav>
</control>
				
			<control name = "c#5#">
					<position>1</position>
			

				<uprav>
					<name>Заземление</name>
					<poloz>подключено</poloz>
				</uprav>

				<luft>
					<left>0</left>
					<right>0</right>
				</luft>

				<UpravWork>
					<proverkaNU>true</proverkaNU>
					<proverkaPZI>true</proverkaPZI>
				</UpravWork>

				<LinkUprav>
					<LinkToIMG>KPAengine\Pic KPA\Спеки.docx</LinkToIMG>
					<vinoska>с5</vinoska>
				</LinkUprav>
</control>
			
			<control name = "e#0#">
				<position>1</position>
			

				<uprav>
					<name>Переключатель «КОНТРОЛЬ U»</name>
					<poloz>в положении «27В РЭД»</poloz>
				</uprav>

				<luft>
					<left>0</left>
					<right>0</right>
				</luft>

				<UpravWork>
					<proverkaNU>true</proverkaNU>
					<proverkaPZI>true</proverkaPZI>
				</UpravWork>

				<LinkUprav>
					<LinkToIMG>KPAengine\Pic KPA\Спеки.docx</LinkToIMG>
					<vinoska>e0</vinoska>
				</LinkUprav>
</control>
			
			<control name = "p#0#">
				<position>100</position>
			

				<uprav>
					<name>Ручка «ВРЕМЯ ИНДИК.»</name>
					<poloz>в крайнем левом положении</poloz>
				</uprav>

				<luft>
					<left>0</left>
					<right>0</right>
				</luft>

				<UpravWork>
					<proverkaNU>true</proverkaNU>
					<proverkaPZI>true</proverkaPZI>
				</UpravWork>

				<LinkUprav>
					<LinkToIMG>KPAengine\Pic KPA\Спеки.docx</LinkToIMG>
					<vinoska>p0</vinoska>
				</LinkUprav>
</control>
			
			<control name = "p#1#">
				<position>0</position>
			

				<uprav>
					<name>Винт «РЕГУЛИРОВКА ηтк» </name>
					<poloz>в крайнем левом положении</poloz>
				</uprav>

				<luft>
					<left>0</left>
					<right>0</right>
				</luft>

				<UpravWork>
					<proverkaNU>true</proverkaNU>
					<proverkaPZI>true</proverkaPZI>
				</UpravWork>

				<LinkUprav>
					<LinkToIMG>KPAengine\Pic KPA\Спеки.docx</LinkToIMG>
					<vinoska>p1</vinoska>
				</LinkUprav>
</control>
			
			<control name = "f#0#">
				<position>1</position>
			

				<uprav>
					<name>Предохранитель «ПР1 1А»</name>
					<poloz>установлен</poloz>
				</uprav>

				<luft>
					<left>0</left>
					<right>0</right>
				</luft>

				<UpravWork>
					<proverkaNU>true</proverkaNU>
					<proverkaPZI>true</proverkaPZI>
				</UpravWork>

				<LinkUprav>
					<LinkToIMG>KPAengine\Pic KPA\Спеки.docx</LinkToIMG>
					<vinoska>f0</vinoska>
				</LinkUprav>
</control>
			
			<control name = "b#0#">
				<position>0</position>
			

				<uprav>
					<name>Выключатель «27В»</name>
					<poloz>в нижнем положении</poloz>
				</uprav>

				<luft>
					<left>0</left>
					<right>0</right>
				</luft>

				<UpravWork>
					<proverkaNU>true</proverkaNU>
					<proverkaPZI>true</proverkaPZI>
				</UpravWork>

				<LinkUprav>
					<LinkToIMG>KPAengine\Pic KPA\Спеки.docx</LinkToIMG>
					<vinoska>b0</vinoska>
				</LinkUprav>
</control>
			
			<control name = "b#1#">
				<position>0</position>
			

				<uprav>
					<name>Переключатель «4СТП»</name>
					<poloz>в нижнем положении</poloz>
				</uprav>

				<luft>
					<left>0</left>
					<right>0</right>
				</luft>

				<UpravWork>
					<proverkaNU>true</proverkaNU>
					<proverkaPZI>true</proverkaPZI>
				</UpravWork>

				<LinkUprav>
					<LinkToIMG>KPAengine\Pic KPA\Спеки.docx</LinkToIMG>
					<vinoska>b1</vinoska>
				</LinkUprav>
</control>
				
			<control name = "b#2#">
				<position>0</position>
			

				<uprav>
					<name>Переключатель «3СТП»</name>
					<poloz>в нижнем положении</poloz>
				</uprav>

				<luft>
					<left>0</left>
					<right>0</right>
				</luft>

				<UpravWork>
					<proverkaNU>true</proverkaNU>
					<proverkaPZI>true</proverkaPZI>
				</UpravWork>

				<LinkUprav>
					<LinkToIMG>KPAengine\Pic KPA\Спеки.docx</LinkToIMG>
					<vinoska>b2</vinoska>
				</LinkUprav>
</control>
			
			<control name = "b#3#">
				<position>0</position>
			

				<uprav>
					<name>Переключатель «2СТП»</name>
					<poloz>в нижнем положении</poloz>
				</uprav>

				<luft>
					<left>0</left>
					<right>0</right>
				</luft>

				<UpravWork>
					<proverkaNU>true</proverkaNU>
					<proverkaPZI>true</proverkaPZI>
				</UpravWork>

				<LinkUprav>
					<LinkToIMG>KPAengine\Pic KPA\Спеки.docx</LinkToIMG>
					<vinoska>b3</vinoska>
				</LinkUprav>
</control>
			
			<control name = "b#4#">
				<position>0</position>
			

				<uprav>
					<name>Переключатель «1СТП»</name>
					<poloz>в нижнем положении</poloz>
				</uprav>

				<luft>
					<left>0</left>
					<right>0</right>
				</luft>

				<UpravWork>
					<proverkaNU>true</proverkaNU>
					<proverkaPZI>true</proverkaPZI>
				</UpravWork>

				<LinkUprav>
					<LinkToIMG>KPAengine\Pic KPA\Спеки.docx</LinkToIMG>
					<vinoska>b4</vinoska>
				</LinkUprav>
</control>
			
			<control name = "b#5#">
				<position>0</position>
			

				<uprav>
					<name>Переключатель «2ПА»</name>
					<poloz>в нижнем положении</poloz>
				</uprav>

				<luft>
					<left>0</left>
					<right>0</right>
				</luft>

				<UpravWork>
					<proverkaNU>true</proverkaNU>
					<proverkaPZI>true</proverkaPZI>
				</UpravWork>

				<LinkUprav>
					<LinkToIMG>KPAengine\Pic KPA\Спеки.docx</LinkToIMG>
					<vinoska>b5</vinoska>
				</LinkUprav>
</control>
			
			<control name = "b#6#">
				<position>0</position>
			

				<uprav>
					<name>Переключатель «1ПА»</name>
					<poloz>в нижнем положении</poloz>
				</uprav>

				<luft>
					<left>0</left>
					<right>0</right>
				</luft>

				<UpravWork>
					<proverkaNU>true</proverkaNU>
					<proverkaPZI>true</proverkaPZI>
				</UpravWork>

				<LinkUprav>
					<LinkToIMG>KPAengine\Pic KPA\Спеки.docx</LinkToIMG>
					<vinoska>b6</vinoska>
				</LinkUprav>
</control>
			
			<control name = "b#7#">
				<position>0</position>
			

				<uprav>
					<name>Переключатель «6ЭП»</name>
					<poloz>в нижнем положении</poloz>
				</uprav>

				<luft>
					<left>0</left>
					<right>0</right>
				</luft>

				<UpravWork>
					<proverkaNU>true</proverkaNU>
					<proverkaPZI>true</proverkaPZI>
				</UpravWork>

				<LinkUprav>
					<LinkToIMG>KPAengine\Pic KPA\Спеки.docx</LinkToIMG>
					<vinoska>b7</vinoska>
				</LinkUprav>
</control>
			
			<control name = "b#8#">
				<position>0</position>
			

				<uprav>
					<name>Переключатель «5ЭП»</name>
					<poloz>в нижнем положении</poloz>
				</uprav>

				<luft>
					<left>0</left>
					<right>0</right>
				</luft>

				<UpravWork>
					<proverkaNU>true</proverkaNU>
					<proverkaPZI>true</proverkaPZI>
				</UpravWork>

				<LinkUprav>
					<LinkToIMG>KPAengine\Pic KPA\Спеки.docx</LinkToIMG>
					<vinoska>b8</vinoska>
				</LinkUprav>
</control>
			
			<control name = "b#9#">
				<position>0</position>
			

				<uprav>
					<name>Переключатель «4ЭП»</name>
					<poloz>в нижнем положении</poloz>
				</uprav>

				<luft>
					<left>0</left>
					<right>0</right>
				</luft>

				<UpravWork>
					<proverkaNU>true</proverkaNU>
					<proverkaPZI>true</proverkaPZI>
				</UpravWork>

				<LinkUprav>
					<LinkToIMG>KPAengine\Pic KPA\Спеки.docx</LinkToIMG>
					<vinoska>b9</vinoska>
				</LinkUprav>
</control>
				
			<control name = "b#10#">
				<position>0</position>
			

				<uprav>
					<name>Переключатель «3ЭП»</name>
					<poloz>в нижнем положении</poloz>
				</uprav>

				<luft>
					<left>0</left>
					<right>0</right>
				</luft>

				<UpravWork>
					<proverkaNU>true</proverkaNU>
					<proverkaPZI>true</proverkaPZI>
				</UpravWork>

				<LinkUprav>
					<LinkToIMG>KPAengine\Pic KPA\Спеки.docx</LinkToIMG>
					<vinoska>b10</vinoska>
				</LinkUprav>
</control>
			
			<control name = "b#11#">
				<position>0</position>
			

				<uprav>
					<name>Переключатель «2ЭП»</name>
					<poloz>в нижнем положении</poloz>
				</uprav>

				<luft>
					<left>0</left>
					<right>0</right>
				</luft>

				<UpravWork>
					<proverkaNU>true</proverkaNU>
					<proverkaPZI>true</proverkaPZI>
				</UpravWork>

				<LinkUprav>
					<LinkToIMG>KPAengine\Pic KPA\Спеки.docx</LinkToIMG>
					<vinoska>b11</vinoska>
				</LinkUprav>
</control>
			
			<control name = "b#12#">
				<position>0</position>
			

				<uprav>
					<name>Переключатель «1ЭП»</name>
					<poloz>в нижнем положении</poloz>
				</uprav>

				<luft>
					<left>0</left>
					<right>0</right>
				</luft>

				<UpravWork>
					<proverkaNU>true</proverkaNU>
					<proverkaPZI>true</proverkaPZI>
				</UpravWork>

				<LinkUprav>
					<LinkToIMG>KPAengine\Pic KPA\Спеки.docx</LinkToIMG>
					<vinoska>b12</vinoska>
				</LinkUprav>
</control>
			
			<control name = "b#13#">
				<position>0</position>
			

				<uprav>
					<name>Переключатель «RGS»</name>
					<poloz>в нижнем положении</poloz>
				</uprav>

				<luft>
					<left>0</left>
					<right>0</right>
				</luft>

				<UpravWork>
					<proverkaNU>true</proverkaNU>
					<proverkaPZI>true</proverkaPZI>
				</UpravWork>

				<LinkUprav>
					<LinkToIMG>KPAengine\Pic KPA\Спеки.docx</LinkToIMG>
					<vinoska>b13</vinoska>
				</LinkUprav>
</control>
			
			<control name = "b#14#">
				<position>0</position>
			

				<uprav>
					<name>Переключатель «БЛηнв»</name>
					<poloz>в нижнем положении</poloz>
				</uprav>

				<luft>
					<left>0</left>
					<right>0</right>
				</luft>

				<UpravWork>
					<proverkaNU>true</proverkaNU>
					<proverkaPZI>true</proverkaPZI>
				</UpravWork>

				<LinkUprav>
					<LinkToIMG>KPAengine\Pic KPA\Спеки.docx</LinkToIMG>
					<vinoska>b14</vinoska>
				</LinkUprav>
</control>
			
			<control name = "b#15#">
				<position>0</position>
			

				<uprav>
					<name>Переключатель «ηст2»</name>
					<poloz>в нижнем положении</poloz>
				</uprav>

				<luft>
					<left>0</left>
					<right>0</right>
				</luft>

				<UpravWork>
					<proverkaNU>true</proverkaNU>
					<proverkaPZI>true</proverkaPZI>
				</UpravWork>

				<LinkUprav>
					<LinkToIMG>KPAengine\Pic KPA\Спеки.docx</LinkToIMG>
					<vinoska>b15</vinoska>
				</LinkUprav>
</control>
			
			<control name = "b#16#">
				<position>0</position>
			

				<uprav>
					<name>Переключатель «ηст1»</name>
					<poloz>в нижнем положении</poloz>
				</uprav>

				<luft>
					<left>0</left>
					<right>0</right>
				</luft>

				<UpravWork>
					<proverkaNU>true</proverkaNU>
					<proverkaPZI>true</proverkaPZI>
				</UpravWork>

				<LinkUprav>
					<LinkToIMG>KPAengine\Pic KPA\Спеки.docx</LinkToIMG>
					<vinoska>b16</vinoska>
				</LinkUprav>
</control>
			
			<control name = "b#17#">
				<position>0</position>
			

				<uprav>
					<name>Переключатель «КОД»</name>
					<poloz>в нижнем положении</poloz>
				</uprav>

				<luft>
					<left>0</left>
					<right>0</right>
				</luft>

				<UpravWork>
					<proverkaNU>true</proverkaNU>
					<proverkaPZI>true</proverkaPZI>
				</UpravWork>

				<LinkUprav>
					<LinkToIMG>KPAengine\Pic KPA\Спеки.docx</LinkToIMG>
					<vinoska>b17</vinoska>
				</LinkUprav>
</control>
			
		</initialPositions>
		
	</device>
	
</devices>